{
  "problem_id": 230,
  "annotation": "",
  "source": "SolidGeo",
  "problem_text_en": "Find L. Give your answer rounded down to the nearest cm.",
  "construction_cdl": [
    "Shape(OP,PO)",
    "Cocircular(O)",
    "Cocircular(P)"
  ],
  "text_cdl": [
    "Equal(HeightOfCylinder(O,P),13)",
    "Equal(RadiusOfCircle(O),3)"
  ],
  "image_cdl": [
    "Cylinder(O,P)",
    "Equal(HeightOfCylinder(O,P),13)",
    "Equal(RadiusOfCircle(O),3)",
    "LengthOfLine(O,P,L)"
  ],
  "goal_cdl": "Value(LengthOfLine(O,P,L))",
  "problem_answer": "13",
  "problem_type": [],
  "complexity_level": "",
  "theorem_seqs": [],
  "theorem_seqs_dag": "{\"START\": []}"
}