{
  "problem_id": 301,
  "annotation": "",
  "annotation_img": "",
  "source": "SolidGeo",
  "problem_text_cn": "",
  "problem_text_en": "",
  "problem_img": [
    "images\\301.jpg"
  ],
  "construction_cdl": [
    "Shape(A,B)",
    "Shape(P,Q)",
    "Shape(C,D)",
    "Cocircular(A)",
    "Cocircular(B)",
    "Cocircular(C)",
    "Cocircular(D)",
    "Cocircular(P)",
    "Cocircular(Q)",
    "Coplanar(U,A)",
    "Coplanar(V,BC)",
    "Coplanar(W,DP)",
    "Coplanar(X,Q)"
  ],
  "text_cdl": [],
  "image_cdl": [
    "Equal(HeightOfCylinder(A,B), 2)",
    "Equal(HeightOfCylinder(P,Q), 2)",
    "Cylinder(C,D)",
    "Cylinder(A,B)",
    "Equal(RadiusOfCircle(A),8)",
    "Equal(RadiusOfCircle(P),8)",
    "Equal(RadiusOfCircle(A), 8)",
    "Equal(HeightOfCylinder(C,D),10)",
    "Cylinder(P,Q)",
    "Equal(RadiusOfCircle(Q), 8)",
    "Equal(DiameterOfCircle(C),3)"
  ],
  "goal_cdl": "Value(Add(VolumeOfCylinder(P,Q),VolumeOfCylinder(C,D),VolumeOfCylinder(A,B)))",
  "problem_answer": "874.93",
  "problem_type": [
    "Measurement of Solid Geometric Forms",
    "Composite Solid Structures"
  ],
  "complexity_level": "Level 2",
  "theorem_seqs": [],
  "theorem_seqs_dag": {
    "START": []
  }
}