{
  "problem_id": 94,
  "annotation": "",
  "source": "SolidGeo",
  "problem_text_en": "Each side length of the cube is equal to 12cm. Find the volume of the cube shown.",
  "construction_cdl": [
    "Shape(AB,BC,CD,DA,EF,FG,GH,HE,AE,BF,CG,DH)",
    "Coplanar(ABCD,EFGH)"
  ],
  "text_cdl": [
    "Equal(SideLengthOfCube(AB),12)"
  ],
  "image_cdl": [
    "Cube(ABCD,EFGH)",
    "Equal(SideLengthOfCube(AB),12)"
  ],
  "goal_cdl": "Value(VolumeOfCube(ABCD,EFGH))",
  "problem_answer": "1728",
  "problem_type": [],
  "complexity_level": "",
  "theorem_seqs": [],
  "theorem_seqs_dag": "{\"START\": []}"
}