{
  "problem_id": 990,
  "annotation": "",
  "annotation_img": "",
  "source": "SolidGeo",
  "problem_text_cn": "",
  "problem_text_en": "",
  "problem_img": [
    "images\\289.jpg"
  ],
  "construction_cdl": [
    "Shape(PQ,QP)",
    "Shape(PA,AC,CB,BP)",
    "Cocircular(P,AB)",
    "Cocircular(Q,C)",
    "Collinear(APB)",
    "Coplanar(U,PAB)",
    "Coplanar(V,QC)",
    "Coplanar(W,PQABC)"
  ],
  "text_cdl": [
    "Cylinder(P,Q)",
    "IsCentreOfCircle(P,P)",
    "IsCentreOfCircle(Q,Q)",
    "Equal(HeightOfCylinder(P,Q),13)",
    "Equal(RadiusOfCircle(P),3)",
    "Equal(LengthOfLine(AC),l)"
  ],
  "image_cdl": [
    "Cylinder(P,Q)",
    "IsCentreOfCircle(P,P)",
    "IsCentreOfCircle(Q,Q)",
    "Equal(HeightOfCylinder(P,Q),13)",
    "Equal(RadiusOfCircle(P),3)",
    "Equal(MeasureOfAngle(ABC),90)"
  ],
  "goal_cdl": "Value(l)",
  "problem_answer": "14",
  "problem_type": [
    "Measurement of Solid Geometric Forms",
    "Spatial Metric Relations"
  ],
  "complexity_level": "Level 2",
  "theorem_seqs": [],
  "theorem_seqs_dag": {
    "START": []
  }
}