{
  "problem_id": 508,
  "annotation": "",
  "source": "SolidGeo",
  "problem_text_en": "As shown in the figure, AB and CD are parallel to each other, and CD is on the plane U. Prove that AB is parallel to plane U.",
  "construction_cdl": [
    "Shape(AB,CD)",
    "Plane(U)",
    "Coplanar(U,CD)"
  ],
  "text_cdl": [
    "ParallelBetweenLine(AB,CD)",
    "Coplanar(U,CD)"
  ],
  "image_cdl": [
    "Shape(AB,CD)",
    "Plane(U)",
    "ParallelBetweenLine(AB,CD)",
    "Coplanar(U,CD)"
  ],
  "goal_cdl": "ParallelBetweenLineAndPlane(AB,U)",
  "problem_answer": "True",
  "problem_type": [],
  "complexity_level": "",
  "theorem_seqs": [],
  "theorem_seqs_dag": "{\"START\": []}"
}